README
setup.py
worldcat/__init__.py
worldcat/exceptions.py
worldcat.egg-info/PKG-INFO
worldcat.egg-info/SOURCES.txt
worldcat.egg-info/dependency_links.txt
worldcat.egg-info/requires.txt
worldcat.egg-info/top_level.txt
worldcat/request/__init__.py
worldcat/request/registry.py
worldcat/request/search.py
worldcat/request/xid.py
worldcat/response/__init__.py
worldcat/response/registry.py
worldcat/response/search.py
worldcat/response/xid.py
worldcat/util/__init__.py
worldcat/util/extract.py
worldcat/util/safeeval.py