Metadata-Version: 1.0
Name: worldcat
Version: 0.3.6
Summary: Interact with OCLC's WorldCat Affiliate APIs
Home-page: http://github.com/anarchivist/worldcat
Author: Mark A. Matienzo
Author-email: mark@matienzo.org
License: GPL/BSD
Platform: UNKNOWN
Classifier: Intended Audience :: Education
Classifier: Intended Audience :: Developers
Classifier: Intended Audience :: Information Technology
Classifier: License :: OSI Approved :: BSD License
Classifier: License :: OSI Approved :: GNU General Public License (GPL)
Classifier: Programming Language :: Python
Classifier: Development Status :: 4 - Beta
